elerium/__init__.py
elerium/__main__.py
elerium/cli.py
elerium/mti_parser.py
elerium/util.py
elerium/warnings.py
elerium-0.2.2.dist-info/entry_points.txt
elerium-0.2.2.dist-info/licenses/LICENSES/MIT.txt
elerium-0.2.2.dist-info/WHEEL
elerium-0.2.2.dist-info/METADATA
elerium-0.2.2.dist-info/RECORD
