Metadata-Version: 2.4
Name: elerium
Version: 0.2.2
Summary: Improve your UFOs
Author-email: Rose Davidson <rose@metaclassical.com>
Requires-Python: >=3.12
License-Expression: MIT
License-File: LICENSES/MIT.txt
Requires-Dist: fontTools>=4.56.0
Requires-Dist: more-itertools>=10.6.0
Requires-Dist: ufoLib2>=0.17.1
Requires-Dist: typer>=0.15.1
Project-URL: Homepage, https://github.com/inklesspen/elerium
Project-URL: Issues, https://github.com/inklesspen/elerium/issues
